{
  "frames": {
    "dirt-11-w:0.png": {
      "frame": {
        "x": 16,
        "y": 0,
        "w": 8,
        "h": 8
      }
    },
    "dirt-12-n:0,w:0.png": {
      "frame": {
        "x": 24,
        "y": 0,
        "w": 8,
        "h": 8
      }
    },
    "dirt-13-n:0,w:0.png": {
      "frame": {
        "x": 32,
        "y": 0,
        "w": 8,
        "h": 8
      }
    },
    "dirt-14-n:0.png": {
      "frame": {
        "x": 40,
        "y": 0,
        "w": 8,
        "h": 8
      }
    },
    "dirt-11-s:0,w:0.png": {
      "frame": {
        "x": 0,
        "y": 8,
        "w": 8,
        "h": 8
      }
    },
    "dirt-12-w:0.png": {
      "frame": {
        "x": 8,
        "y": 8,
        "w": 8,
        "h": 8
      }
    },
    "dirt-21-s:1.png": {
      "frame": {
        "x": 16,
        "y": 8,
        "w": 8,
        "h": 8
      }
    },
    "dirt-22-u:!.png": {
      "frame": {
        "x": 24,
        "y": 8,
        "w": 8,
        "h": 8
      }
    },
    "dirt-23-u:!.png": {
      "frame": {
        "x": 32,
        "y": 8,
        "w": 8,
        "h": 8
      }
    },
    "dirt-24-e:1.png": {
      "frame": {
        "x": 40,
        "y": 8,
        "w": 8,
        "h": 8
      }
    },
    "dirt-13-n:0.png": {
      "frame": {
        "x": 48,
        "y": 8,
        "w": 8,
        "h": 8
      }
    },
    "dirt-14-n:0,e:0.png": {
      "frame": {
        "x": 56,
        "y": 8,
        "w": 8,
        "h": 8
      }
    },
    "dirt-21-u:!,s:0,w:0.png": {
      "frame": {
        "x": 0,
        "y": 16,
        "w": 8,
        "h": 8
      }
    },
    "dirt-22-u:!,s:!.png": {
      "frame": {
        "x": 8,
        "y": 16,
        "w": 8,
        "h": 8
      }
    },
    "dirt-11-w:1.png": {
      "frame": {
        "x": 16,
        "y": 16,
        "w": 8,
        "h": 8
      }
    },
    "dirt-12-w:1.png": {
      "frame": {
        "x": 24,
        "y": 16,
        "w": 8,
        "h": 8
      }
    },
    "dirt-13-n:1.png": {
      "frame": {
        "x": 32,
        "y": 16,
        "w": 8,
        "h": 8
      }
    },
    "dirt-14-n:1.png": {
      "frame": {
        "x": 40,
        "y": 16,
        "w": 8,
        "h": 8
      }
    },
    "dirt-23-u:!,e:!.png": {
      "frame": {
        "x": 48,
        "y": 16,
        "w": 8,
        "h": 8
      }
    },
    "dirt-24-u:!,n:0,e:0.png": {
      "frame": {
        "x": 56,
        "y": 16,
        "w": 8,
        "h": 8
      }
    },
    "dirt-21-u:!,s:!.png": {
      "frame": {
        "x": 16,
        "y": 24,
        "w": 8,
        "h": 8
      }
    },
    "dirt-22-u:!,e:0,s:0.png": {
      "frame": {
        "x": 24,
        "y": 24,
        "w": 8,
        "h": 8
      }
    },
    "dirt-23-u:!,e:0,s:0.png": {
      "frame": {
        "x": 32,
        "y": 24,
        "w": 8,
        "h": 8
      }
    },
    "dirt-24-u:!,e:!.png": {
      "frame": {
        "x": 40,
        "y": 24,
        "w": 8,
        "h": 8
      }
    }
  },
  "meta": {
    "app": "https://www.codeandweb.com/texturepacker",
    "version": "1.1",
    "image": "dirt.png",
    "format": "RGBA8888",
    "size": {
      "w": 64,
      "h": 96
    },
    "scale": "1"
  }
}
